CHANGELOG.txt
LICENCE.txt
MANIFEST.in
README.txt
requirements.txt
setup.py
Row/run.py
Venv/Lib/site-packages/easy_install.py
Venv/Lib/site-packages/six.py
Venv/Lib/site-packages/certifi/__init__.py
Venv/Lib/site-packages/certifi/__main__.py
Venv/Lib/site-packages/certifi/core.py
Venv/Lib/site-packages/certifi-2020.12.5.dist-info/top_level.txt
Venv/Lib/site-packages/chardet/__init__.py
Venv/Lib/site-packages/chardet/big5freq.py
Venv/Lib/site-packages/chardet/big5prober.py
Venv/Lib/site-packages/chardet/chardistribution.py
Venv/Lib/site-packages/chardet/charsetgroupprober.py
Venv/Lib/site-packages/chardet/charsetprober.py
Venv/Lib/site-packages/chardet/codingstatemachine.py
Venv/Lib/site-packages/chardet/compat.py
Venv/Lib/site-packages/chardet/cp949prober.py
Venv/Lib/site-packages/chardet/enums.py
Venv/Lib/site-packages/chardet/escprober.py
Venv/Lib/site-packages/chardet/escsm.py
Venv/Lib/site-packages/chardet/eucjpprober.py
Venv/Lib/site-packages/chardet/euckrfreq.py
Venv/Lib/site-packages/chardet/euckrprober.py
Venv/Lib/site-packages/chardet/euctwfreq.py
Venv/Lib/site-packages/chardet/euctwprober.py
Venv/Lib/site-packages/chardet/gb2312freq.py
Venv/Lib/site-packages/chardet/gb2312prober.py
Venv/Lib/site-packages/chardet/hebrewprober.py
Venv/Lib/site-packages/chardet/jisfreq.py
Venv/Lib/site-packages/chardet/jpcntx.py
Venv/Lib/site-packages/chardet/langbulgarianmodel.py
Venv/Lib/site-packages/chardet/langgreekmodel.py
Venv/Lib/site-packages/chardet/langhebrewmodel.py
Venv/Lib/site-packages/chardet/langhungarianmodel.py
Venv/Lib/site-packages/chardet/langrussianmodel.py
Venv/Lib/site-packages/chardet/langthaimodel.py
Venv/Lib/site-packages/chardet/langturkishmodel.py
Venv/Lib/site-packages/chardet/latin1prober.py
Venv/Lib/site-packages/chardet/mbcharsetprober.py
Venv/Lib/site-packages/chardet/mbcsgroupprober.py
Venv/Lib/site-packages/chardet/mbcssm.py
Venv/Lib/site-packages/chardet/sbcharsetprober.py
Venv/Lib/site-packages/chardet/sbcsgroupprober.py
Venv/Lib/site-packages/chardet/sjisprober.py
Venv/Lib/site-packages/chardet-4.0.0.dist-info/entry_points.txt
Venv/Lib/site-packages/chardet-4.0.0.dist-info/top_level.txt
Venv/Lib/site-packages/idna-2.10.dist-info/top_level.txt
Venv/Lib/site-packages/numpy-1.20.2.dist-info/LICENSE.txt
Venv/Lib/site-packages/numpy-1.20.2.dist-info/LICENSES_bundled.txt
Venv/Lib/site-packages/numpy-1.20.2.dist-info/entry_points.txt
Venv/Lib/site-packages/numpy-1.20.2.dist-info/top_level.txt
Venv/Lib/site-packages/pandas-1.2.4.dist-info/entry_points.txt
Venv/Lib/site-packages/pandas-1.2.4.dist-info/top_level.txt
Venv/Lib/site-packages/pip-19.2.3.dist-info/LICENSE.txt
Venv/Lib/site-packages/pip-19.2.3.dist-info/entry_points.txt
Venv/Lib/site-packages/pip-19.2.3.dist-info/top_level.txt
Venv/Lib/site-packages/python_dateutil-2.8.1.dist-info/top_level.txt
Venv/Lib/site-packages/pytz-2021.1.dist-info/LICENSE.txt
Venv/Lib/site-packages/pytz-2021.1.dist-info/top_level.txt
Venv/Lib/site-packages/requests-2.25.1.dist-info/top_level.txt
Venv/Lib/site-packages/setuptools-41.2.0.dist-info/dependency_links.txt
Venv/Lib/site-packages/setuptools-41.2.0.dist-info/entry_points.txt
Venv/Lib/site-packages/setuptools-41.2.0.dist-info/top_level.txt
Venv/Lib/site-packages/six-1.16.0.dist-info/top_level.txt
Venv/Lib/site-packages/urllib3-1.26.4.dist-info/LICENSE.txt
Venv/Lib/site-packages/urllib3-1.26.4.dist-info/top_level.txt
cowinvacc.egg-info/PKG-INFO
cowinvacc.egg-info/SOURCES.txt
cowinvacc.egg-info/dependency_links.txt
cowinvacc.egg-info/requires.txt
cowinvacc.egg-info/top_level.txt