Metadata-Version: 1.2
Name: cowinvacc
Version: 0.0.2
Summary: Cowin Tracker for Covid-19 vaccine usng CoWin APIs.
Home-page: https://github.com/anajikadam17/cowinvacc.git
Author: anajikadam17
Author-email: anajikadam17@gmail.com
License: MIT
Keywords: cowin,covid,vaccine,cowinvacc
Platform: UNKNOWN
Classifier: Development Status :: 5 - Production/Stable
Classifier: Intended Audience :: Education
Classifier: Operating System :: Microsoft :: Windows :: Windows 10
Classifier: License :: OSI Approved :: MIT License
Classifier: Programming Language :: Python :: 3
Requires-Python: >=3.6, <4
